mlcli/__init__.py
mlcli/main.py
mlcli/commands/__init__.py
mlcli/commands/deploy_cmd.py
mlcli/commands/evaluate_cmd.py
mlcli/commands/init_cmd.py
mlcli/commands/monitor_cmd.py
mlcli/commands/package_cmd.py
mlcli/commands/predict_cmd.py
mlcli/commands/preprocess_cmd.py
mlcli/commands/rollback_cmd.py
mlcli/commands/suggest_cmd.py
mlcli/commands/train_cmd.py
mlcli/core/__init__.py
mlcli/core/config.py
mlcli/core/data.py
mlcli/core/exceptions.py
mlcli/core/models.py
mlcli/utils/__init__.py
mlcli/utils/logging.py
ml_assistant_cli-0.2.0.dist-info/METADATA
ml_assistant_cli-0.2.0.dist-info/WHEEL
ml_assistant_cli-0.2.0.dist-info/entry_points.txt
ml_assistant_cli-0.2.0.dist-info/licenses/LICENSE
ml_assistant_cli-0.2.0.dist-info/RECORD
