Metadata-Version: 2.4
Name: ml-assistant-cli
Version: 0.2.0
Summary: End-to-end ML workflow CLI - from dataset to deployed API
Project-URL: Homepage, https://github.com/mlcli/mlcli
Project-URL: Documentation, https://mlcli.readthedocs.io
Project-URL: Repository, https://github.com/mlcli/mlcli
Project-URL: Issues, https://github.com/mlcli/mlcli/issues
Author: ML Assistant CLI Team
License-Expression: MIT
License-File: LICENSE
Keywords: bentoml,cli,deployment,machine-learning,mlops
Classifier: Development Status :: 4 - Beta
Classifier: Intended Audience :: Developers
Classifier: License :: OSI Approved :: MIT License
Classifier: Programming Language :: Python :: 3
Classifier: Programming Language :: Python :: 3.9
Classifier: Programming Language :: Python :: 3.10
Classifier: Programming Language :: Python :: 3.11
Classifier: Programming Language :: Python :: 3.12
Classifier: Topic :: Scientific/Engineering :: Artificial Intelligence
Classifier: Topic :: Software Development :: Libraries :: Python Modules
Requires-Python: >=3.9
Requires-Dist: bentoml>=1.2.0
Requires-Dist: click>=8.0.0
Requires-Dist: httpx>=0.24.0
Requires-Dist: matplotlib>=3.5.0
Requires-Dist: pandas>=2.0.0
Requires-Dist: pathlib-mate>=1.0.0
Requires-Dist: pydantic>=2.0.0
Requires-Dist: pyyaml>=6.0
Requires-Dist: rich>=13.0.0
Requires-Dist: scikit-learn>=1.3.0
Requires-Dist: seaborn>=0.11.0
Requires-Dist: typer[all]>=0.9.0
Requires-Dist: xgboost>=1.7.0
Provides-Extra: cloud
Requires-Dist: azure-ai-ml>=1.12.0; extra == 'cloud'
Requires-Dist: azure-identity>=1.15.0; extra == 'cloud'
Requires-Dist: boto3>=1.34.0; extra == 'cloud'
Requires-Dist: sagemaker>=2.200.0; extra == 'cloud'
Provides-Extra: dev
Requires-Dist: black>=23.0.0; extra == 'dev'
Requires-Dist: isort>=5.12.0; extra == 'dev'
Requires-Dist: mypy>=1.0.0; extra == 'dev'
Requires-Dist: pre-commit>=3.0.0; extra == 'dev'
Requires-Dist: pytest-cov>=4.0.0; extra == 'dev'
Requires-Dist: pytest>=7.0.0; extra == 'dev'
Requires-Dist: ruff>=0.1.0; extra == 'dev'
